{
	"format_version": "1.12.0",
	"minecraft:geometry": [
		{
			"description": {
				"identifier": "geometry.unknown",
				"texture_width": 64,
				"texture_height": 64,
				"visible_bounds_width": 3,
				"visible_bounds_height": 2.5,
				"visible_bounds_offset": [0, 0.75, 0]
			},
			"bones": [
				{
					"name": "Chicken",
					"pivot": [0, 0, 0]
				},
				{
					"name": "Body",
					"parent": "Chicken",
					"pivot": [-0.10887, 13.56502, 2.36135],
					"cubes": [
						{
							"origin": [-2.60887, 5.66502, -6.13865],
							"size": [5.2, 6.4, 8.5],
							"pivot": [-0.00887, 6.66502, -5.63865],
							"rotation": [-15, 0, 0],
							"uv": {
								"north": {"uv": [20, 18], "uv_size": [5, 6]},
								"east": {"uv": [10, 0], "uv_size": [9, 6]},
								"south": {"uv": [7, 21], "uv_size": [5, 6]},
								"west": {"uv": [10, 6], "uv_size": [9, 6]},
								"up": {"uv": [10, 12], "uv_size": [5, 9]},
								"down": {"uv": [15, 21], "uv_size": [5, -9]}
							}
						}
					]
				},
				{
					"name": "Tail",
					"parent": "Body",
					"pivot": [0.04759, 8.8682, 1.4014],
					"rotation": [7.5, 0, 0],
					"cubes": [
						{
							"origin": [-1.75241, 4.7682, 1.3014],
							"size": [3.6, 6, 4.4],
							"pivot": [0.04759, 5.7682, 3.4014],
							"rotation": [7.5, 0, 0],
							"uv": {
								"north": {"uv": [12, 21], "uv_size": [4, 6]},
								"east": {"uv": [16, 21], "uv_size": [4, 6]},
								"south": {"uv": [0, 22], "uv_size": [4, 6]},
								"west": {"uv": [20, 24], "uv_size": [4, 6]},
								"up": {"uv": [7, 27], "uv_size": [4, 4]},
								"down": {"uv": [11, 31], "uv_size": [4, -4]}
							}
						}
					]
				},
				{
					"name": "Tail1",
					"parent": "Tail",
					"pivot": [-0.3182, 9.89946, 2.70556],
					"cubes": [
						{
							"origin": [-0.0832, 8.85948, -0.30959],
							"size": [0.0832, 7.7372, 10.3172],
							"inflate": 0.01,
							"pivot": [-0.043, 9.64888, 1.51764],
							"rotation": [-25, 0, 0],
							"uv": {
								"north": {"uv": [6, 29], "uv_size": [1, 8]},
								"east": {"uv": [0, 0], "uv_size": [10, 8]},
								"south": {"uv": [30, 12], "uv_size": [1, 8]},
								"west": {"uv": [0, 8], "uv_size": [10, 8]},
								"up": {"uv": [19, 27], "uv_size": [1, 10]},
								"down": {"uv": [27, 32], "uv_size": [1, -10]}
							}
						}
					]
				},
				{
					"name": "Wings",
					"parent": "Body",
					"pivot": [-0.3182, 0, 0]
				},
				{
					"name": "RWing",
					"parent": "Wings",
					"pivot": [-2.91153, 9.2278, -1.84556],
					"cubes": [
						{
							"origin": [-3.42925, 5.58397, -4.29536],
							"size": [0.85907, 4.29536, 5.15443],
							"pivot": [-2.97921, 8.7468, -3.66219],
							"rotation": [5, 0, 0],
							"uv": {
								"north": {"uv": [11, 34], "uv_size": [1, 4]},
								"east": {"uv": [25, 18], "uv_size": [5, 4]},
								"south": {"uv": [12, 34], "uv_size": [1, 4]},
								"west": {"uv": [26, 0], "uv_size": [5, 4]},
								"up": {"uv": [5, 32], "uv_size": [1, 5]},
								"down": {"uv": [27, 37], "uv_size": [1, -5]}
							}
						}
					]
				},
				{
					"name": "RWingEnd",
					"parent": "RWing",
					"pivot": [-3.73373, 9.65477, -3.69112],
					"cubes": [
						{
							"origin": [-3.00292, 3.80762, -4.22431],
							"size": [0.43275, 5.7875, 7.42816],
							"pivot": [-2.97921, 8.7468, -3.66219],
							"rotation": [-10, 0, 0],
							"uv": {
								"north": {"uv": [2, 31], "uv_size": [1, 6]},
								"east": {"uv": [0, 16], "uv_size": [7, 6]},
								"south": {"uv": [26, 31], "uv_size": [1, 6]},
								"west": {"uv": [19, 0], "uv_size": [7, 6]},
								"up": {"uv": [20, 30], "uv_size": [1, 7]},
								"down": {"uv": [21, 37], "uv_size": [1, -7]}
							}
						}
					]
				},
				{
					"name": "LWing",
					"parent": "Wings",
					"pivot": [2.91153, 9.2278, -1.84556],
					"cubes": [
						{
							"origin": [2.57018, 5.58397, -4.29536],
							"size": [0.85907, 4.29536, 5.15443],
							"pivot": [2.97921, 8.7468, -3.66219],
							"rotation": [5, 0, 0],
							"uv": {
								"north": {"uv": [34, 12], "uv_size": [1, 4]},
								"east": {"uv": [26, 4], "uv_size": [5, 4]},
								"south": {"uv": [13, 34], "uv_size": [1, 4]},
								"west": {"uv": [26, 8], "uv_size": [5, 4]},
								"up": {"uv": [33, 0], "uv_size": [1, 5]},
								"down": {"uv": [33, 10], "uv_size": [1, -5]}
							}
						}
					]
				},
				{
					"name": "LWingEnd",
					"parent": "LWing",
					"pivot": [3.73373, 9.65477, -3.69112],
					"cubes": [
						{
							"origin": [2.57018, 3.80762, -4.22431],
							"size": [0.43275, 5.7875, 7.42816],
							"pivot": [2.97921, 8.7468, -3.66219],
							"rotation": [-10, 0, 0],
							"uv": {
								"north": {"uv": [30, 31], "uv_size": [1, 6]},
								"east": {"uv": [19, 6], "uv_size": [7, 6]},
								"south": {"uv": [31, 31], "uv_size": [1, 6]},
								"west": {"uv": [20, 12], "uv_size": [7, 6]},
								"up": {"uv": [22, 30], "uv_size": [1, 7]},
								"down": {"uv": [23, 37], "uv_size": [1, -7]}
							}
						}
					]
				},
				{
					"name": "Neck",
					"parent": "Body",
					"pivot": [0.04261, 10.41792, -5.74903]
				},
				{
					"name": "Thick",
					"parent": "Neck",
					"pivot": [-0.3182, 9.2278, -4.6139],
					"cubes": [
						{
							"origin": [-1.1, 7.0278, -6.0139],
							"size": [2.2, 7, 3],
							"pivot": [0.0818, 8.0278, -5.0139],
							"rotation": [-12.5, 0, 0],
							"uv": {
								"north": {"uv": [15, 27], "uv_size": [2, 7]},
								"east": {"uv": [4, 22], "uv_size": [3, 7]},
								"south": {"uv": [17, 27], "uv_size": [2, 7]},
								"west": {"uv": [24, 24], "uv_size": [3, 7]},
								"up": {"uv": [3, 32], "uv_size": [2, 3]},
								"down": {"uv": [32, 34], "uv_size": [2, -3]}
							}
						},
						{
							"origin": [-0.93207, 12.21466, -5.27203],
							"size": [1.86116, 2.54823, 2.77145],
							"pivot": [-0.00149, 13.72069, -3.77035],
							"rotation": [42.5, 0, 0],
							"uv": {
								"north": {"uv": [7, 31], "uv_size": [2, 3]},
								"east": {"uv": [27, 15], "uv_size": [3, 3]},
								"south": {"uv": [9, 31], "uv_size": [2, 3]},
								"west": {"uv": [0, 28], "uv_size": [3, 3]},
								"up": {"uv": [31, 9], "uv_size": [2, 3]},
								"down": {"uv": [11, 34], "uv_size": [2, -3]}
							}
						}
					]
				},
				{
					"name": "Head",
					"parent": "Thick",
					"pivot": [-0.3182, 13.8417, -3.69112],
					"cubes": [
						{
							"origin": [-1, 13, -6.3],
							"size": [2, 2.6, 2.9],
							"uv": {
								"north": {"uv": [31, 12], "uv_size": [2, 3]},
								"east": {"uv": [28, 22], "uv_size": [3, 3]},
								"south": {"uv": [13, 31], "uv_size": [2, 3]},
								"west": {"uv": [28, 25], "uv_size": [3, 3]},
								"up": {"uv": [31, 15], "uv_size": [2, 3]},
								"down": {"uv": [31, 25], "uv_size": [2, -3]}
							}
						},
						{
							"origin": [-0.28771, 13.0701, -7.42879],
							"size": [0.66271, 0.95337, 1.61996],
							"pivot": [0.36033, 13.78065, -6.6188],
							"rotation": [17.5, 0, 0],
							"uv": {
								"north": {"uv": [35, 3], "uv_size": [1, 1]},
								"east": {"uv": [34, 17], "uv_size": [2, 1]},
								"south": {"uv": [4, 35], "uv_size": [1, 1]},
								"west": {"uv": [34, 18], "uv_size": [2, 1]},
								"up": {"uv": [18, 34], "uv_size": [1, 2]},
								"down": {"uv": [34, 21], "uv_size": [1, -2]}
							}
						},
						{
							"origin": [0.0444, 14.1914, -6.5346],
							"size": [-0.0028, 2.4052, 3.4372],
							"inflate": 0.01,
							"pivot": [0.086, 15.69297, -4.85494],
							"rotation": [2.5, 0, 0],
							"uv": {
								"north": {"uv": [0, 0], "uv_size": [0, 2]},
								"east": {"uv": [7, 19], "uv_size": [3, 2]},
								"south": {"uv": [0, 0], "uv_size": [0, 2]},
								"west": {"uv": [30, 20], "uv_size": [3, 2]},
								"up": {"uv": [0, 0], "uv_size": [0, 3]},
								"down": {"uv": [0, 3], "uv_size": [0, -3]}
							}
						},
						{
							"origin": [0.4314, 12.0414, -5.7606],
							"size": [0.0832, 1.7172, 1.7172],
							"inflate": 0.01,
							"pivot": [0.59494, 13.09728, -4.96518],
							"rotation": [7.5, 0, 0],
							"uv": {
								"north": {"uv": [34, 21], "uv_size": [1, 2]},
								"east": {"uv": [33, 26], "uv_size": [2, 2]},
								"south": {"uv": [34, 23], "uv_size": [1, 2]},
								"west": {"uv": [33, 28], "uv_size": [2, 2]},
								"up": {"uv": [24, 34], "uv_size": [1, 2]},
								"down": {"uv": [25, 36], "uv_size": [1, -2]}
							}
						},
						{
							"origin": [-0.5146, 12.0414, -5.7606],
							"size": [0.0832, 1.7172, 1.7172],
							"inflate": 0.01,
							"pivot": [-0.59494, 13.09728, -4.96518],
							"rotation": [7.5, 0, 0],
							"uv": {
								"north": {"uv": [35, 21], "uv_size": [-1, 2]},
								"east": {"uv": [35, 28], "uv_size": [-2, 2]},
								"south": {"uv": [35, 23], "uv_size": [-1, 2]},
								"west": {"uv": [35, 26], "uv_size": [-2, 2]},
								"up": {"uv": [25, 34], "uv_size": [-1, 2]},
								"down": {"uv": [26, 36], "uv_size": [-1, -2]}
							}
						}
					]
				},
				{
					"name": "Legs",
					"parent": "Body",
					"pivot": [-0.04079, 5.97685, 0]
				},
				{
					"name": "LeftLeg",
					"parent": "Legs",
					"pivot": [1.76422, 5.0285, 1.53406]
				},
				{
					"name": "LThigh",
					"parent": "LeftLeg",
					"pivot": [1.52736, 4.6139, -0.92278],
					"cubes": [
						{
							"origin": [0.63726, 3.43629, -2.05636],
							"size": [2.14768, 2.57722, 2.91543],
							"pivot": [1.51109, 4.75175, -0.46856],
							"rotation": [7.5, 0, 0],
							"uv": {
								"north": {"uv": [0, 31], "uv_size": [2, 3]},
								"east": {"uv": [7, 16], "uv_size": [3, 3]},
								"south": {"uv": [31, 0], "uv_size": [2, 3]},
								"west": {"uv": [27, 12], "uv_size": [3, 3]},
								"up": {"uv": [31, 3], "uv_size": [2, 3]},
								"down": {"uv": [31, 9], "uv_size": [2, -3]}
							}
						}
					]
				},
				{
					"name": "LLeg",
					"parent": "LThigh",
					"pivot": [1.29325, 3.69112, 0],
					"cubes": [
						{
							"origin": [0.98154, 0.01848, -0.58246],
							"size": [0.75906, 3.79532, 0.96199],
							"uv": {
								"north": {"uv": [33, 10], "uv_size": [1, 4]},
								"east": {"uv": [33, 14], "uv_size": [1, 4]},
								"south": {"uv": [33, 18], "uv_size": [1, 4]},
								"west": {"uv": [33, 22], "uv_size": [1, 4]},
								"up": {"uv": [3, 28], "uv_size": [1, 1]},
								"down": {"uv": [3, 36], "uv_size": [1, -1]}
							}
						}
					]
				},
				{
					"name": "LFoot",
					"parent": "LLeg",
					"pivot": [1.71957, 0.1156, -0.24825],
					"cubes": [
						{
							"origin": [0.63726, 0, -1.71814],
							"size": [1.71814, 0.08591, 1.71814],
							"uv": {
								"north": {"uv": [33, 30], "uv_size": [2, 1]},
								"east": {"uv": [14, 34], "uv_size": [2, 1]},
								"south": {"uv": [16, 34], "uv_size": [2, 1]},
								"west": {"uv": [34, 16], "uv_size": [2, 1]},
								"up": {"uv": [25, 22], "uv_size": [2, 2]},
								"down": {"uv": [31, 20], "uv_size": [2, -2]}
							}
						}
					]
				},
				{
					"name": "RightLeg",
					"parent": "Legs",
					"pivot": [-1.76422, 5.0285, 1.53406]
				},
				{
					"name": "RThigh",
					"parent": "RightLeg",
					"pivot": [-1.52736, 4.6139, -0.92278],
					"cubes": [
						{
							"origin": [-2.78494, 3.43629, -2.05636],
							"size": [2.14768, 2.57722, 2.91543],
							"pivot": [-1.51109, 4.75175, -0.46856],
							"rotation": [7.5, 0, 0],
							"uv": {
								"north": {"uv": [24, 31], "uv_size": [2, 3]},
								"east": {"uv": [28, 28], "uv_size": [3, 3]},
								"south": {"uv": [31, 25], "uv_size": [2, 3]},
								"west": {"uv": [3, 29], "uv_size": [3, 3]},
								"up": {"uv": [28, 31], "uv_size": [2, 3]},
								"down": {"uv": [31, 31], "uv_size": [2, -3]}
							}
						}
					]
				},
				{
					"name": "RLeg",
					"parent": "RThigh",
					"pivot": [-1.29325, 3.69112, 0],
					"cubes": [
						{
							"origin": [-1.74061, 0.01848, -0.58246],
							"size": [0.75906, 3.79532, 0.96199],
							"uv": {
								"north": {"uv": [34, 2], "uv_size": [1, 4]},
								"east": {"uv": [34, 6], "uv_size": [1, 4]},
								"south": {"uv": [7, 34], "uv_size": [1, 4]},
								"west": {"uv": [8, 34], "uv_size": [1, 4]},
								"up": {"uv": [35, 4], "uv_size": [1, 1]},
								"down": {"uv": [35, 6], "uv_size": [1, -1]}
							}
						}
					]
				},
				{
					"name": "RFoot",
					"parent": "RLeg",
					"pivot": [-1.71957, 0.1156, -0.24825],
					"cubes": [
						{
							"origin": [-2.35541, 0, -1.71814],
							"size": [1.71814, 0.08591, 1.71814],
							"uv": {
								"north": {"uv": [34, 25], "uv_size": [2, 1]},
								"east": {"uv": [33, 34], "uv_size": [2, 1]},
								"south": {"uv": [34, 33], "uv_size": [2, 1]},
								"west": {"uv": [35, 2], "uv_size": [2, 1]},
								"up": {"uv": [9, 34], "uv_size": [2, 2]},
								"down": {"uv": [34, 12], "uv_size": [2, -2]}
							}
						}
					]
				}
			]
		}
	]
}